MANIFEST.in
requirements.txt
setup.py
test_requirements.txt
version.txt
cloudshell/__init__.py
cloudshell/traffic/__init__.py
cloudshell/traffic/trex/__init__.py
cloudshell/traffic/trex/cli/__init__.py
cloudshell/traffic/trex/cli/trex_cli_handler.py
cloudshell/traffic/trex/cli/trex_command_modes.py
cloudshell/traffic/trex/client/__init__.py
cloudshell/traffic/trex/client/trex_client/CCustomLogger.py
cloudshell/traffic/trex/client/trex_client/__init__.py
cloudshell/traffic/trex/client/trex_client/external_packages.py
cloudshell/traffic/trex/client/trex_client/general_utils.py
cloudshell/traffic/trex/client/trex_client/outer_packages.py
cloudshell/traffic/trex/client/trex_client/simple_enum.py
cloudshell/traffic/trex/client/trex_client/text_opts.py
cloudshell/traffic/trex/client/trex_client/trex_client.py
cloudshell/traffic/trex/client/trex_client/trex_daemon_server.py
cloudshell/traffic/trex/client/trex_client/trex_exceptions.py
cloudshell/traffic/trex/client/trex_client/trex_status.py
cloudshell/traffic/trex/client/trex_client/trex_status_e.py
cloudshell/traffic/trex/command_templates/__init__.py
cloudshell/traffic/trex/command_templates/trex_autoload.py
cloudshell/traffic/trex/command_templates/trex_common.py
cloudshell_tg_trex.egg-info/PKG-INFO
cloudshell_tg_trex.egg-info/SOURCES.txt
cloudshell_tg_trex.egg-info/dependency_links.txt
cloudshell_tg_trex.egg-info/requires.txt
cloudshell_tg_trex.egg-info/top_level.txt
tests/__init__.py