Metadata-Version: 1.0
Name: cloudshell-tg-trex
Version: 1.0.0
Summary: QualiSystems Python package
Home-page: https://github.com/QualiSystems/cloudshell-tg-trex
Author: QualiSystems
Author-email: info@qualisystems.com
License: UNKNOWN
Platform: UNKNOWN
